TakeSparkSpellChecker/__init__.py
TakeSparkSpellChecker/sparkspellcheck.py
TakeSpellChecker/__init__.py
TakeSpellChecker/spellcheck.py
TakeSparkSpellChecker-0.0.6.dist-info/LICENSE
TakeSparkSpellChecker-0.0.6.dist-info/METADATA
TakeSparkSpellChecker-0.0.6.dist-info/WHEEL
TakeSparkSpellChecker-0.0.6.dist-info/top_level.txt
TakeSparkSpellChecker-0.0.6.dist-info/RECORD
