Metadata-Version: 2.1
Name: TakeSparkSpellChecker
Version: 0.0.6
Summary: Machine learning spell check package that combines word's context with characters similarity.
Home-page: UNKNOWN
Author: Karina Tiemi Kato
Author-email: karinatkato@gmail.com
License: UNKNOWN
Platform: UNKNOWN
Classifier: Programming Language :: Python :: 3
Classifier: License :: OSI Approved :: MIT License
Classifier: Operating System :: OS Independent
Requires-Dist: numpy
Requires-Dist: gensim
Requires-Dist: pyjarowinkler (==1.8)
